{
	"match": {
		"competition": "National League",
		"date": "Tuesday 25th October 2016",
		"time": "19:45:00",
		"status": "Full Time",
		"teams": [
			{
				"side": "home",
				"no": "293",
				"name": "Guiseley",
				"halfTimeScore": "0",
				"score": "1",
				"goals": [
					{
						"goal": "Simon Walton (pen 65')"
					}
				],
				"players": [
					{
						"shirtNo": "26",
						"name": "Jonathan Maxted"
					},
					{
						"shirtNo": "3",
						"name": "Danny Lowe"
					},
					{
						"shirtNo": "6",
						"name": "Jake Lawlor"
					},
					{
						"shirtNo": "23",
						"name": "Danny East",
						"caution": {
							"minute": "90"
						}
					},
					{
						"shirtNo": "18",
						"name": "Nicky Clee",
						"substitution": {
							"replacedBy": "Adam Boyes",
							"minute": "81"
						}
					},
					{
						"shirtNo": "8",
						"name": "Will Hatfield"
					},
					{
						"shirtNo": "22",
						"name": "Alex Purver"
					},
					{
						"shirtNo": "24",
						"name": "Simon Walton"
					},
					{
						"shirtNo": "25",
						"name": "Rob Atkinson"
					},
					{
						"shirtNo": "29",
						"name": "Jake Cassidy"
					},
					{
						"shirtNo": "31",
						"name": "James Wesolowski"
					},
					{
						"shirtNo": "17",
						"name": "Daniel Atkinson"
					},
					{
						"shirtNo": "9",
						"name": "Adam Boyes"
					},
					{
						"shirtNo": "11",
						"name": "Michael Rankine"
					},
					{
						"shirtNo": "15",
						"name": "Ashley Palmer"
					},
					{
						"shirtNo": "19",
						"name": "Jordan Preston"
					}
				]
			},
			{
				"side": "away",
				"no": "292",
				"name": "Gateshead",
				"halfTimeScore": "0",
				"score": "1",
				"goals": [
					{
						"goal": "Danny Johnson (86')"
					}
				],
				"players": [
					{
						"shirtNo": "13",
						"name": "Dan Hanford"
					},
					{
						"shirtNo": "3",
						"name": "George Smith",
						"substitution": {
							"replacedBy": "Reece Styche",
							"minute": "69"
						}
					},
					{
						"shirtNo": "4",
						"name": "Manny Smith"
					},
					{
						"shirtNo": "9",
						"name": "Danny Johnson"
					},
					{
						"shirtNo": "7",
						"name": "Wesley York"
					},
					{
						"shirtNo": "5",
						"name": "Liam Hogan"
					},
					{
						"shirtNo": "8",
						"name": "Mitch Brundle"
					},
					{
						"shirtNo": "10",
						"name": "Sam Jones"
					},
					{
						"shirtNo": "19",
						"name": "Dan Jones"
					},
					{
						"shirtNo": "16",
						"name": "Russell Penn"
					},
					{
						"shirtNo": "25",
						"name": "Luke Hannant",
						"substitution": {
							"replacedBy": "Wesley Atkinson",
							"minute": "63"
						}
					},
					{
						"shirtNo": "1",
						"name": "Sam Johnson"
					},
					{
						"shirtNo": "12",
						"name": "Wesley Atkinson"
					},
					{
						"shirtNo": "17",
						"name": "Reece Styche"
					},
					{
						"shirtNo": "20",
						"name": "Adam Wrightson"
					},
					{
						"shirtNo": "22",
						"name": "Augustin Mafuta"
					}
				]
			}
		],
		"attendance": "762",
		"venue": "Nethermoor Park"
	}
}

